setup.cfg
setup.py
bencode/__init__.py
bencode_py3.egg-info/PKG-INFO
bencode_py3.egg-info/SOURCES.txt
bencode_py3.egg-info/dependency_links.txt
bencode_py3.egg-info/top_level.txt
bencode_py3.egg-info/zip-safe
test/__init__.py
test/benchmarkbencode.py
test/benchmarkdata.py
test/testbencode.py