Metadata-Version: 1.1
Name: bencode-py3
Version: 1.1329139006
Summary: The BitTorrent bencode module as light-weight, standalone package, ported to Python 3
Home-page: https://github.com/JoshRodd/bencode_py3
Author: Josh Rodd
Author-email: josh@rodd.us
License: BitTorrent Open Source License
Download-URL: https://github.com/JoshRodd/bencode_py3/archive/1.1329139006.tar.gz
Keywords: bittorrent bencode bdecode python3 bencode_py3
Platform: UNKNOWN
